fsl/shift32/shift32.v
/*
 * This code is produced by: 
 *   FSL Compiler version 0.1 alpha (2020-05-08) build 20E313
 *   Designed by Nobuya WATANABE, Okayama University, 2015-2020.
 * 
 *   Mon May 18 15:09:33 JST 2020
 * 
 * The source file of this code: 'shift32.fsl'.
 * 
 * INFO: 
 * 
 */
/* ModuleDef: shift32 */

module shift32(p_reset, m_clock, in, shamt, out, sll, srl, sra);
  input         p_reset;
  wire          p_reset;
  input         m_clock;
  wire          m_clock;
  input  [31:0] in;
  wire   [31:0] in;
  input   [4:0] shamt;
  wire    [4:0] shamt;
  output [31:0] out;
  wire   [31:0] out;
  input         sll;
  wire          sll;
  input         srl;
  wire          srl;
  input         sra;
  wire          sra;
  /* for bundle-type input/output */
  /* local decls */
  wire          __net0;
  wire          __net1;
  wire          __net10;
  wire          __net11;
  wire          __net12;
  wire          __net13;
  wire          __net2;
  wire          __net3;
  wire          __net4;
  wire          __net5;
  wire   [31:0] __net6;
  wire          __net7;
  wire   [31:0] __net8;
  wire          __net9;
  wire   [31:0] _shift_right_in;
  wire   [31:0] _shift_right_result_;
  wire          _shift_right_s01;
  wire    [1:0] _shift_right_s02_1_1010;
  wire    [3:0] _shift_right_s04_1_1011;
  wire    [7:0] _shift_right_s08_1_1012;
  wire   [15:0] _shift_right_s16_1_1013;
  wire   [31:0] _shift_right_t1_1_1014;
  wire   [31:0] _shift_right_t2_1_1015;
  wire   [31:0] _shift_right_t3_1_1016;
  wire   [31:0] _shift_right_t4_1_1017;
  wire   [31:0] _shift_right_t5_1_1018;
  wire          _sll_s01_0_1000;
  wire    [1:0] _sll_s02_0_1001;
  wire    [3:0] _sll_s04_0_1002;
  wire    [7:0] _sll_s08_0_1003;
  wire   [15:0] _sll_s16_0_1004;
  wire   [31:0] _sll_t1_0_1005;
  wire   [31:0] _sll_t2_0_1006;
  wire   [31:0] _sll_t3_0_1007;
  wire   [31:0] _sll_t4_0_1008;
  wire   [31:0] _sll_t5_0_1009;
  wire          shift_right;
  /* assigns */
  assign __net0 = sll ? shamt[0] == 1'B1 ? 1'b1 : 1'b0 : 1'bx;
  assign __net1 = sll ? shamt[1] == 1'B1 ? 1'b1 : 1'b0 : 1'bx;
  assign __net10 = shift_right ? shamt[1] == 1'B1 ? 1'b1 : 1'b0 : 1'bx;
  assign __net11 = shift_right ? shamt[2] == 1'B1 ? 1'b1 : 1'b0 : 1'bx;
  assign __net12 = shift_right ? shamt[3] == 1'B1 ? 1'b1 : 1'b0 : 1'bx;
  assign __net13 = shift_right ? shamt[4] == 1'B1 ? 1'b1 : 1'b0 : 1'bx;
  assign __net2 = sll ? shamt[2] == 1'B1 ? 1'b1 : 1'b0 : 1'bx;
  assign __net3 = sll ? shamt[3] == 1'B1 ? 1'b1 : 1'b0 : 1'bx;
  assign __net4 = sll ? shamt[4] == 1'B1 ? 1'b1 : 1'b0 : 1'bx;
  assign __net5 = srl ? 1'B0 : 1'bx;
  assign __net6 = srl ? in : 32'bx;
  assign __net7 = sra ? in[31] : 1'bx;
  assign __net8 = sra ? in : 32'bx;
  assign __net9 = shift_right ? shamt[0] == 1'B1 ? 1'b1 : 1'b0 : 1'bx;
  assign _shift_right_in = srl ? __net6 : sra ? __net8 : 32'bx;
  assign _shift_right_result_ = shift_right ? _shift_right_t5_1_1018 : 32'bx;
  assign _shift_right_s01 = srl ? __net5 : sra ? __net7 : 1'bx;
  assign _shift_right_s02_1_1010 = shift_right ? 
                                     {_shift_right_s01, _shift_right_s01} : 
                                     2'bx;
  assign _shift_right_s04_1_1011 = shift_right ? 
                                     {_shift_right_s02_1_1010, _shift_right_s02_1_1010} : 
                                     4'bx;
  assign _shift_right_s08_1_1012 = shift_right ? 
                                     {_shift_right_s04_1_1011, _shift_right_s04_1_1011} : 
                                     8'bx;
  assign _shift_right_s16_1_1013 = shift_right ? 
                                     {_shift_right_s08_1_1012, _shift_right_s08_1_1012} : 
                                     16'bx;
  assign _shift_right_t1_1_1014 = shift_right ? 
                                    shamt[0] == 1'B1 ? 
                                      {_shift_right_s01, _shift_right_in[31:1]} : 
                                      _shift_right_in : 
                                    32'bx;
  assign _shift_right_t2_1_1015 = shift_right ? 
                                    shamt[1] == 1'B1 ? 
                                      {_shift_right_s02_1_1010, _shift_right_t1_1_1014[31:2]} : 
                                      _shift_right_t1_1_1014 : 
                                    32'bx;
  assign _shift_right_t3_1_1016 = shift_right ? 
                                    shamt[2] == 1'B1 ? 
                                      {_shift_right_s04_1_1011, _shift_right_t2_1_1015[31:4]} : 
                                      _shift_right_t2_1_1015 : 
                                    32'bx;
  assign _shift_right_t4_1_1017 = shift_right ? 
                                    shamt[3] == 1'B1 ? 
                                      {_shift_right_s08_1_1012, _shift_right_t3_1_1016[31:8]} : 
                                      _shift_right_t3_1_1016 : 
                                    32'bx;
  assign _shift_right_t5_1_1018 = shift_right ? 
                                    shamt[4] == 1'B1 ? 
                                      {_shift_right_s16_1_1013, _shift_right_t4_1_1017[31:16]} : 
                                      _shift_right_t4_1_1017 : 
                                    32'bx;
  assign _sll_s01_0_1000 = sll ? 1'B0 : 1'bx;
  assign _sll_s02_0_1001 = sll ? 2'B00 : 2'bx;
  assign _sll_s04_0_1002 = sll ? 4'B0000 : 4'bx;
  assign _sll_s08_0_1003 = sll ? 8'B00000000 : 8'bx;
  assign _sll_s16_0_1004 = sll ? 16'B0000000000000000 : 16'bx;
  assign _sll_t1_0_1005 = sll ? 
                            shamt[0] == 1'B1 ? 
                              {in[30:0], 1'B0} : 
                              in : 
                            32'bx;
  assign _sll_t2_0_1006 = sll ? 
                            shamt[1] == 1'B1 ? 
                              {_sll_t1_0_1005[29:0], 2'B00} : 
                              _sll_t1_0_1005 : 
                            32'bx;
  assign _sll_t3_0_1007 = sll ? 
                            shamt[2] == 1'B1 ? 
                              {_sll_t2_0_1006[27:0], 4'B0000} : 
                              _sll_t2_0_1006 : 
                            32'bx;
  assign _sll_t4_0_1008 = sll ? 
                            shamt[3] == 1'B1 ? 
                              {_sll_t3_0_1007[23:0], 8'B00000000} : 
                              _sll_t3_0_1007 : 
                            32'bx;
  assign _sll_t5_0_1009 = sll ? 
                            shamt[4] == 1'B1 ? 
                              {_sll_t4_0_1008[15:0], 16'B0000000000000000} : 
                              _sll_t4_0_1008 : 
                            32'bx;
  assign out = sra ? 
                 _shift_right_result_ : 
                 srl ? 
                   _shift_right_result_ : 
                   sll ? 
                     _sll_t5_0_1009 : 
                     32'bx;
  /* invokes */
  /* private function */
  assign shift_right = srl | sra;
  /* defs */
  /* FunDef sll */
  /*   parameter: in: Bit(32) */
  /*   parameter: shamt: Bit(5) */
  /* FunDef srl */
  /*   parameter: in: Bit(32) */
  /*   parameter: shamt: Bit(5) */
  /* FunDef sra */
  /*   parameter: in: Bit(32) */
  /*   parameter: shamt: Bit(5) */
endmodule
/* End of file (shift32.v) */

fsl/shift32/test_shift32.v
/*
 * This code is produced by: 
 *   FSL Compiler version 0.1 alpha (2020-05-08) build 20E313
 *   Designed by Nobuya WATANABE, Okayama University, 2015-2020.
 * 
 *   Mon May 18 15:09:33 JST 2020
 * 
 * The source file of this code: 'test_shift32.fsl'.
 * 
 * INFO: 
 * 
 */
/* ModuleDef: test_shift32 */

module test_shift32(p_reset, m_clock);
  input        p_reset;
  wire         p_reset;
  input        m_clock;
  wire         m_clock;
  /* for bundle-type input/output */
  /* decls */
  /* ModuleInstance: s0: ___no_package___.shift32 */
  wire         _s0_p_reset;
  wire         _s0_m_clock;
  wire         _s0_srl;
  wire         _s0_sll;
  wire  [31:0] _s0_in;
  wire  [31:0] _s0_out;
  wire         _s0_sra;
  wire   [4:0] _s0_shamt;
  shift32 s0(.p_reset(_s0_p_reset),
             .m_clock(_s0_m_clock),
             .srl(_s0_srl),
             .sll(_s0_sll),
             .in(_s0_in),
             .out(_s0_out),
             .sra(_s0_sra),
             .shamt(_s0_shamt));
  /* reg decl */
  reg   [11:0] count;
  /* MemDecl pat (BitType 40) size: IConst(128,128) */
  reg   [39:0] pat[0:127];
  /* local decls */
  wire         __net0;
  wire         __net1;
  wire         __net10;
  wire  [31:0] __net11;
  wire   [4:0] __net12;
  wire         __net13;
  wire  [11:0] __net2;
  wire   [2:0] __net3;
  wire         __net4;
  wire  [31:0] __net5;
  wire   [4:0] __net6;
  wire         __net7;
  wire  [31:0] __net8;
  wire   [4:0] __net9;
  wire   [2:0] fun;
  wire  [11:0] i;
  wire  [31:0] in;
  wire  [31:0] out;
  wire  [39:0] p;
  wire   [4:0] shamt;
  /* reg decls (system) */
  reg   [63:0] _time;
  /* assigns */
  assign __net0 = _time == 64'b10 ? 1'b1 : 1'b0;
  assign __net1 = 2 <= count && count <= 129 ? 1'b1 : 1'b0;
  assign __net10 = __net1 ? __net3 == 3'B001 ? 1'b1 : 1'b0 : 1'bx;
  assign __net11 = ~(__net1 & __net7) & (~(__net1 & __net4) & (__net1 & __net10)) ? 
                     in : 
                     32'bx;
  assign __net12 = ~(__net1 & __net7) & (~(__net1 & __net4) & (__net1 & __net10)) ? 
                     shamt : 
                     5'bx;
  assign __net13 = count == 129 ? 1'b1 : 1'b0;
  assign __net2 = __net1 ? i : 12'bx;
  assign __net3 = __net1 ? fun : 3'bx;
  assign __net4 = __net1 ? __net3 == 3'B100 ? 1'b1 : 1'b0 : 1'bx;
  assign __net5 = __net1 & __net4 ? in : 32'bx;
  assign __net6 = __net1 & __net4 ? shamt : 5'bx;
  assign __net7 = __net1 ? __net3 == 3'B010 ? 1'b1 : 1'b0 : 1'bx;
  assign __net8 = ~(__net1 & __net4) & (__net1 & __net7) ? in : 32'bx;
  assign __net9 = ~(__net1 & __net4) & (__net1 & __net7) ? shamt : 5'bx;
  assign _s0_in = __net1 & __net4 ? 
                    __net5 : 
                    ~(__net1 & __net4) & (__net1 & __net7) ? 
                      __net8 : 
                      ~(__net1 & __net7) & (~(__net1 & __net4) & (__net1 & __net10)) ? 
                        __net11 : 
                        32'bx;
  assign _s0_m_clock = m_clock;
  assign _s0_p_reset = p_reset;
  assign _s0_shamt = __net1 & __net4 ? 
                       __net6 : 
                       ~(__net1 & __net4) & (__net1 & __net7) ? 
                         __net9 : 
                         ~(__net1 & __net7) & (~(__net1 & __net4) & (__net1 & __net10)) ? 
                           __net12 : 
                           5'bx;
  assign _s0_sll = __net1 & __net4 ? 1'b1 : 1'b0;
  assign _s0_sra = ~(__net1 & __net7) & (~(__net1 & __net4) & (__net1 & __net10)) ? 
                     1'b1 : 
                     1'b0;
  assign _s0_srl = ~(__net1 & __net4) & (__net1 & __net7) ? 1'b1 : 1'b0;
  assign fun = __net1 ? p[2:0] : 3'bx;
  assign i = __net1 ? count + 12'B111111111110 : 12'bx;
  assign in = __net1 ? p[39:8] : 32'bx;
  assign out = __net1 ? _s0_out : 32'bx;
  assign p = __net1 ? pat[__net2] : 40'bx;
  assign shamt = __net1 ? p[7:3] : 5'bx;
  /* defs */
  /* initial */
  /* always */
  /* reg updates */
  always @(posedge m_clock or posedge p_reset)
    begin
      if (p_reset)
        count <= 12'b0;
      else
        count <= count + 12'B000000000001;
    end
  /* reg updates (system) */
  always @(posedge m_clock)
    begin
      _time <= _time + 64'b1;
    end
  /* always */
  always @(posedge m_clock)
    if (__net13)
      $display("bye");
  always @(posedge m_clock)
    if (__net13)
      $finish();
  always @(posedge m_clock)
    if (__net1)
      $display("%d %x %2d %b - %8x", i, in, shamt, fun, out);
  always @(posedge m_clock)
    if (__net0)
      $readmemb("test_shift32.pat", pat);
  /* initial (system) */
  initial begin
    _time <= 64'b0;
  end
endmodule
/* test bench: 'tb' */

module tb;
  parameter CYCLE_TIME = 10;
  reg p_reset;
  reg m_clock;
  test_shift32 test_shift32_instance(.p_reset(p_reset),
                                     .m_clock(m_clock));
  initial begin
    forever #(CYCLE_TIME / 2) m_clock = ~m_clock;
  end
  initial begin
    $dumpfile("test_shift32.vcd");
    $dumpvars(0, test_shift32_instance);
  end
  initial begin
    #(CYCLE_TIME / 10) begin
      p_reset = 1;
      m_clock = 0;
    end
    #CYCLE_TIME p_reset = 0;
  end
endmodule
/* End of file (test_shift32.v) */

fsl/shift32/test_shift32.vcd
$date
	Mon May 18 15:09:44 2020
$end
$version
	Icarus Verilog
$end
$timescale
	1s
$end
$scope module tb $end
$scope module test_shift32_instance $end
$var wire 1 ! _s0_m_clock $end
$var wire 1 " _s0_p_reset $end
$var wire 1 # m_clock $end
$var wire 1 $ p_reset $end
$var wire 5 % shamt [4:0] $end
$var wire 40 & p [39:0] $end
$var wire 32 ' out [31:0] $end
$var wire 32 ( in [31:0] $end
$var wire 12 ) i [11:0] $end
$var wire 3 * fun [2:0] $end
$var wire 1 + _s0_srl $end
$var wire 1 , _s0_sra $end
$var wire 1 - _s0_sll $end
$var wire 5 . _s0_shamt [4:0] $end
$var wire 32 / _s0_out [31:0] $end
$var wire 32 0 _s0_in [31:0] $end
$var wire 5 1 __net9 [4:0] $end
$var wire 32 2 __net8 [31:0] $end
$var wire 1 3 __net7 $end
$var wire 5 4 __net6 [4:0] $end
$var wire 32 5 __net5 [31:0] $end
$var wire 1 6 __net4 $end
$var wire 3 7 __net3 [2:0] $end
$var wire 12 8 __net2 [11:0] $end
$var wire 1 9 __net13 $end
$var wire 5 : __net12 [4:0] $end
$var wire 32 ; __net11 [31:0] $end
$var wire 1 < __net10 $end
$var wire 1 = __net1 $end
$var wire 1 > __net0 $end
$var reg 64 ? _time [63:0] $end
$var reg 12 @ count [11:0] $end
$scope module s0 $end
$var wire 32 A in [31:0] $end
$var wire 1 ! m_clock $end
$var wire 1 " p_reset $end
$var wire 5 B shamt [4:0] $end
$var wire 1 C shift_right $end
$var wire 1 - sll $end
$var wire 1 , sra $end
$var wire 1 + srl $end
$var wire 32 D out [31:0] $end
$var wire 32 E _sll_t5_0_1009 [31:0] $end
$var wire 32 F _sll_t4_0_1008 [31:0] $end
$var wire 32 G _sll_t3_0_1007 [31:0] $end
$var wire 32 H _sll_t2_0_1006 [31:0] $end
$var wire 32 I _sll_t1_0_1005 [31:0] $end
$var wire 16 J _sll_s16_0_1004 [15:0] $end
$var wire 8 K _sll_s08_0_1003 [7:0] $end
$var wire 4 L _sll_s04_0_1002 [3:0] $end
$var wire 2 M _sll_s02_0_1001 [1:0] $end
$var wire 1 N _sll_s01_0_1000 $end
$var wire 32 O _shift_right_t5_1_1018 [31:0] $end
$var wire 32 P _shift_right_t4_1_1017 [31:0] $end
$var wire 32 Q _shift_right_t3_1_1016 [31:0] $end
$var wire 32 R _shift_right_t2_1_1015 [31:0] $end
$var wire 32 S _shift_right_t1_1_1014 [31:0] $end
$var wire 16 T _shift_right_s16_1_1013 [15:0] $end
$var wire 8 U _shift_right_s08_1_1012 [7:0] $end
$var wire 4 V _shift_right_s04_1_1011 [3:0] $end
$var wire 2 W _shift_right_s02_1_1010 [1:0] $end
$var wire 1 X _shift_right_s01 $end
$var wire 32 Y _shift_right_result_ [31:0] $end
$var wire 32 Z _shift_right_in [31:0] $end
$var wire 1 [ __net9 $end
$var wire 32 \ __net8 [31:0] $end
$var wire 1 ] __net7 $end
$var wire 32 ^ __net6 [31:0] $end
$var wire 1 _ __net5 $end
$var wire 1 ` __net4 $end
$var wire 1 a __net3 $end
$var wire 1 b __net2 $end
$var wire 1 c __net13 $end
$var wire 1 d __net12 $end
$var wire 1 e __net11 $end
$var wire 1 f __net10 $end
$var wire 1 g __net1 $end
$var wire 1 h __net0 $end
$upscope $end
$upscope $end
$upscope $end
$enddefinitions $end
#0
$dumpvars
xh
xg
xf
xe
xd
xc
xb
xa
x`
x_
bx ^
x]
bx \
x[
bx Z
bx Y
xX
bx W
bx V
bx U
bx T
bx S
bx R
bx Q
bx P
bx O
xN
bx M
bx L
bx K
bx J
bx I
bx H
bx G
bx F
bx E
bx D
xC
bx B
bx A
bx @
b0 ?
0>
x=
x<
bx ;
bx :
x9
bx 8
bx 7
x6
bx 5
bx 4
x3
bx 2
bx 1
bx 0
bx /
bx .
x-
x,
x+
bx *
bx )
bx (
bx '
bx &
bx %
x$
x#
x"
x!
$end
#1
0C
0,
0+
0-
0=
09
b0 @
0!
0#
1"
1$
#5
b1 ?
1!
1#
#10
0!
0#
#11
0"
0$
#15
1>
b10 ?
b1 @
1!
1#
#20
0!
0#
#25
b10001000100010010001000100010 '
b10001000100010010001000100010 /
b10001000100010010001000100010 D
b10001000100010010001000100010 E
b10001000100010010001000100010 F
b10001000100010010001000100010 G
0h
0g
0b
0a
0`
b10001000100010010001000100010 H
0N
b0 M
b0 L
b0 K
b0 J
b10001000100010010001000100010 I
b0 .
b0 B
b10001000100010010001000100010 0
b10001000100010010001000100010 A
b0 4
b10001000100010010001000100010 5
16
03
0<
b100 7
b0 %
b10001000100010010001000100010 (
b100 *
0C
0,
0+
b1000100010001001000100010001000000100 &
1-
b0 8
b0 )
1=
0>
b11 ?
b10 @
1!
1#
#30
0!
0#
#35
b100010001000100100010001000100 '
b100010001000100100010001000100 /
b100010001000100100010001000100 D
b100010001000100100010001000100 E
b100010001000100100010001000100 F
b100010001000100100010001000100 G
b100010001000100100010001000100 H
1h
b100010001000100100010001000100 I
b1 .
b1 B
b1 4
b1 %
b1000100010001001000100010001000001100 &
b1 8
b1 )
b100 ?
b11 @
1!
1#
#40
0!
0#
#45
b1000100010001001000100010001000 '
b1000100010001001000100010001000 /
b1000100010001001000100010001000 D
b1000100010001001000100010001000 E
b1000100010001001000100010001000 F
b1000100010001001000100010001000 G
0h
1g
b10001000100010010001000100010 I
b1000100010001001000100010001000 H
b10 .
b10 B
b10 4
b10 %
b1000100010001001000100010001000010100 &
b10 8
b10 )
b101 ?
b100 @
1!
1#
#50
0!
0#
#55
b10001000100010010001000100010000 '
b10001000100010010001000100010000 /
b10001000100010010001000100010000 D
b10001000100010010001000100010000 E
b10001000100010010001000100010000 F
b10001000100010010001000100010000 G
b10001000100010010001000100010000 H
1h
b100010001000100100010001000100 I
b11 .
b11 B
b11 4
b11 %
b1000100010001001000100010001000011100 &
b11 8
b11 )
b110 ?
b101 @
1!
1#
#60
0!
0#
#65
b10001000100100010001000100000 '
b10001000100100010001000100000 /
b10001000100100010001000100000 D
b10001000100100010001000100000 E
b10001000100100010001000100000 F
0h
0g
1b
b10001000100010010001000100010 I
b10001000100010010001000100010 H
b10001000100100010001000100000 G
b100 .
b100 B
b100 4
b100 %
b1000100010001001000100010001000100100 &
b100 8
b100 )
b111 ?
b110 @
1!
1#
#70
0!
0#
#75
b100010001001000100010001000000 '
b100010001001000100010001000000 /
b100010001001000100010001000000 D
b100010001001000100010001000000 E
b100010001001000100010001000000 F
b100010001001000100010001000000 G
b100010001000100100010001000100 H
1h
b100010001000100100010001000100 I
b101 .
b101 B
b101 4
b101 %
b1000100010001001000100010001000101100 &
b101 8
b101 )
b1000 ?
b111 @
1!
1#
#80
0!
0#
#85
b1000100010010001000100010000000 '
b1000100010010001000100010000000 /
b1000100010010001000100010000000 D
b1000100010010001000100010000000 E
b1000100010010001000100010000000 F
b1000100010010001000100010000000 G
0h
1g
b10001000100010010001000100010 I
b1000100010001001000100010001000 H
b110 .
b110 B
b110 4
b110 %
b1000100010001001000100010001000110100 &
b110 8
b110 )
b1001 ?
b1000 @
1!
1#
#90
0!
0#
#95
b10001000100100010001000100000000 '
b10001000100100010001000100000000 /
b10001000100100010001000100000000 D
b10001000100100010001000100000000 E
b10001000100100010001000100000000 F
b10001000100100010001000100000000 G
b10001000100010010001000100010000 H
1h
b100010001000100100010001000100 I
b111 .
b111 B
b111 4
b111 %
b1000100010001001000100010001000111100 &
b111 8
b111 )
b1010 ?
b1001 @
1!
1#
#100
0!
0#
#105
b10001001000100010001000000000 '
b10001001000100010001000000000 /
b10001001000100010001000000000 D
b10001001000100010001000000000 E
0h
0g
0b
1a
b10001000100010010001000100010 I
b10001000100010010001000100010 H
b10001000100010010001000100010 G
b10001001000100010001000000000 F
b1000 .
b1000 B
b1000 4
b1000 %
b1000100010001001000100010001001000100 &
b1000 8
b1000 )
b1011 ?
b1010 @
1!
1#
#110
0!
0#
#115
b100010010001000100010000000000 '
b100010010001000100010000000000 /
b100010010001000100010000000000 D
b100010010001000100010000000000 E
b100010010001000100010000000000 F
b100010001000100100010001000100 G
b100010001000100100010001000100 H
1h
b100010001000100100010001000100 I
b1001 .
b1001 B
b1001 4
b1001 %
b1000100010001001000100010001001001100 &
b1001 8
b1001 )
b1100 ?
b1011 @
1!
1#
#120
0!
0#
#125
b1000100100010001000100000000000 '
b1000100100010001000100000000000 /
b1000100100010001000100000000000 D
b1000100100010001000100000000000 E
b1000100100010001000100000000000 F
b1000100010001001000100010001000 G
0h
1g
b10001000100010010001000100010 I
b1000100010001001000100010001000 H
b1010 .
b1010 B
b1010 4
b1010 %
b1000100010001001000100010001001010100 &
b1010 8
b1010 )
b1101 ?
b1100 @
1!
1#
#130
0!
0#
#135
b10001001000100010001000000000000 '
b10001001000100010001000000000000 /
b10001001000100010001000000000000 D
b10001001000100010001000000000000 E
b10001001000100010001000000000000 F
b10001000100010010001000100010000 G
b10001000100010010001000100010000 H
1h
b100010001000100100010001000100 I
b1011 .
b1011 B
b1011 4
b1011 %
b1000100010001001000100010001001011100 &
b1011 8
b1011 )
b1110 ?
b1101 @
1!
1#
#140
0!
0#
#145
b10010001000100010000000000000 '
b10010001000100010000000000000 /
b10010001000100010000000000000 D
b10010001000100010000000000000 E
b10010001000100010000000000000 F
0h
0g
1b
b10001000100010010001000100010 I
b10001000100010010001000100010 H
b10001000100100010001000100000 G
b1100 .
b1100 B
b1100 4
b1100 %
b1000100010001001000100010001001100100 &
b1100 8
b1100 )
b1111 ?
b1110 @
1!
1#
#150
0!
0#
#155
b100100010001000100000000000000 '
b100100010001000100000000000000 /
b100100010001000100000000000000 D
b100100010001000100000000000000 E
b100100010001000100000000000000 F
b100010001001000100010001000000 G
b100010001000100100010001000100 H
1h
b100010001000100100010001000100 I
b1101 .
b1101 B
b1101 4
b1101 %
b1000100010001001000100010001001101100 &
b1101 8
b1101 )
b10000 ?
b1111 @
1!
1#
#160
0!
0#
#165
b1001000100010001000000000000000 '
b1001000100010001000000000000000 /
b1001000100010001000000000000000 D
b1001000100010001000000000000000 E
b1001000100010001000000000000000 F
b1000100010010001000100010000000 G
0h
1g
b10001000100010010001000100010 I
b1000100010001001000100010001000 H
b1110 .
b1110 B
b1110 4
b1110 %
b1000100010001001000100010001001110100 &
b1110 8
b1110 )
b10001 ?
b10000 @
1!
1#
#170
0!
0#
#175
b10010001000100010000000000000000 '
b10010001000100010000000000000000 /
b10010001000100010000000000000000 D
b10010001000100010000000000000000 E
b10010001000100010000000000000000 F
b10001000100100010001000100000000 G
b10001000100010010001000100010000 H
1h
b100010001000100100010001000100 I
b1111 .
b1111 B
b1111 4
b1111 %
b1000100010001001000100010001001111100 &
b1111 8
b1111 )
b10010 ?
b10001 @
1!
1#
#180
0!
0#
#185
b100010001000100000000000000000 '
b100010001000100000000000000000 /
b100010001000100000000000000000 D
0h
0g
0b
0a
1`
b10001000100010010001000100010 I
b10001000100010010001000100010 H
b10001000100010010001000100010 G
b10001000100010010001000100010 F
b100010001000100000000000000000 E
b10000 .
b10000 B
b10000 4
b10000 %
b1000100010001001000100010001010000100 &
b10000 8
b10000 )
b10011 ?
b10010 @
1!
1#
#190
0!
0#
#195
b1000100010001000000000000000000 '
b1000100010001000000000000000000 /
b1000100010001000000000000000000 D
b1000100010001000000000000000000 E
b100010001000100100010001000100 F
b100010001000100100010001000100 G
b100010001000100100010001000100 H
1h
b100010001000100100010001000100 I
b10001 .
b10001 B
b10001 4
b10001 %
b1000100010001001000100010001010001100 &
b10001 8
b10001 )
b10100 ?
b10011 @
1!
1#
#200
0!
0#
#205
b10001000100010000000000000000000 '
b10001000100010000000000000000000 /
b10001000100010000000000000000000 D
b10001000100010000000000000000000 E
b1000100010001001000100010001000 F
b1000100010001001000100010001000 G
0h
1g
b10001000100010010001000100010 I
b1000100010001001000100010001000 H
b10010 .
b10010 B
b10010 4
b10010 %
b1000100010001001000100010001010010100 &
b10010 8
b10010 )
b10101 ?
b10100 @
1!
1#
#210
0!
0#
#215
b10001000100000000000000000000 '
b10001000100000000000000000000 /
b10001000100000000000000000000 D
b10001000100000000000000000000 E
b10001000100010010001000100010000 F
b10001000100010010001000100010000 G
b10001000100010010001000100010000 H
1h
b100010001000100100010001000100 I
b10011 .
b10011 B
b10011 4
b10011 %
b1000100010001001000100010001010011100 &
b10011 8
b10011 )
b10110 ?
b10101 @
1!
1#
#220
0!
0#
#225
b100010001000000000000000000000 '
b100010001000000000000000000000 /
b100010001000000000000000000000 D
b100010001000000000000000000000 E
b10001000100100010001000100000 F
0h
0g
1b
b10001000100010010001000100010 I
b10001000100010010001000100010 H
b10001000100100010001000100000 G
b10100 .
b10100 B
b10100 4
b10100 %
b1000100010001001000100010001010100100 &
b10100 8
b10100 )
b10111 ?
b10110 @
1!
1#
#230
0!
0#
#235
b1000100010000000000000000000000 '
b1000100010000000000000000000000 /
b1000100010000000000000000000000 D
b1000100010000000000000000000000 E
b100010001001000100010001000000 F
b100010001001000100010001000000 G
b100010001000100100010001000100 H
1h
b100010001000100100010001000100 I
b10101 .
b10101 B
b10101 4
b10101 %
b1000100010001001000100010001010101100 &
b10101 8
b10101 )
b11000 ?
b10111 @
1!
1#
#240
0!
0#
#245
b10001000100000000000000000000000 '
b10001000100000000000000000000000 /
b10001000100000000000000000000000 D
b10001000100000000000000000000000 E
b1000100010010001000100010000000 F
b1000100010010001000100010000000 G
0h
1g
b10001000100010010001000100010 I
b1000100010001001000100010001000 H
b10110 .
b10110 B
b10110 4
b10110 %
b1000100010001001000100010001010110100 &
b10110 8
b10110 )
b11001 ?
b11000 @
1!
1#
#250
0!
0#
#255
b10001000000000000000000000000 '
b10001000000000000000000000000 /
b10001000000000000000000000000 D
b10001000000000000000000000000 E
b10001000100100010001000100000000 F
b10001000100100010001000100000000 G
b10001000100010010001000100010000 H
1h
b100010001000100100010001000100 I
b10111 .
b10111 B
b10111 4
b10111 %
b1000100010001001000100010001010111100 &
b10111 8
b10111 )
b11010 ?
b11001 @
1!
1#
#260
0!
0#
#265
b100010000000000000000000000000 '
b100010000000000000000000000000 /
b100010000000000000000000000000 D
b100010000000000000000000000000 E
0h
0g
0b
1a
b10001000100010010001000100010 I
b10001000100010010001000100010 H
b10001000100010010001000100010 G
b10001001000100010001000000000 F
b11000 .
b11000 B
b11000 4
b11000 %
b1000100010001001000100010001011000100 &
b11000 8
b11000 )
b11011 ?
b11010 @
1!
1#
#270
0!
0#
#275
b1000100000000000000000000000000 '
b1000100000000000000000000000000 /
b1000100000000000000000000000000 D
b1000100000000000000000000000000 E
b100010010001000100010000000000 F
b100010001000100100010001000100 G
b100010001000100100010001000100 H
1h
b100010001000100100010001000100 I
b11001 .
b11001 B
b11001 4
b11001 %
b1000100010001001000100010001011001100 &
b11001 8
b11001 )
b11100 ?
b11011 @
1!
1#
#280
0!
0#
#285
b10001000000000000000000000000000 '
b10001000000000000000000000000000 /
b10001000000000000000000000000000 D
b10001000000000000000000000000000 E
b1000100100010001000100000000000 F
b1000100010001001000100010001000 G
0h
1g
b10001000100010010001000100010 I
b1000100010001001000100010001000 H
b11010 .
b11010 B
b11010 4
b11010 %
b1000100010001001000100010001011010100 &
b11010 8
b11010 )
b11101 ?
b11100 @
1!
1#
#290
0!
0#
#295
b10000000000000000000000000000 '
b10000000000000000000000000000 /
b10000000000000000000000000000 D
b10000000000000000000000000000 E
b10001001000100010001000000000000 F
b10001000100010010001000100010000 G
b10001000100010010001000100010000 H
1h
b100010001000100100010001000100 I
b11011 .
b11011 B
b11011 4
b11011 %
b1000100010001001000100010001011011100 &
b11011 8
b11011 )
b11110 ?
b11101 @
1!
1#
#300
0!
0#
#305
b100000000000000000000000000000 '
b100000000000000000000000000000 /
b100000000000000000000000000000 D
b100000000000000000000000000000 E
b10010001000100010000000000000 F
0h
0g
1b
b10001000100010010001000100010 I
b10001000100010010001000100010 H
b10001000100100010001000100000 G
b11100 .
b11100 B
b11100 4
b11100 %
b1000100010001001000100010001011100100 &
b11100 8
b11100 )
b11111 ?
b11110 @
1!
1#
#310
0!
0#
#315
b1000000000000000000000000000000 '
b1000000000000000000000000000000 /
b1000000000000000000000000000000 D
b1000000000000000000000000000000 E
b100100010001000100000000000000 F
b100010001001000100010001000000 G
b100010001000100100010001000100 H
1h
b100010001000100100010001000100 I
b11101 .
b11101 B
b11101 4
b11101 %
b1000100010001001000100010001011101100 &
b11101 8
b11101 )
b100000 ?
b11111 @
1!
1#
#320
0!
0#
#325
b10000000000000000000000000000000 '
b10000000000000000000000000000000 /
b10000000000000000000000000000000 D
b10000000000000000000000000000000 E
b1001000100010001000000000000000 F
b1000100010010001000100010000000 G
0h
1g
b10001000100010010001000100010 I
b1000100010001001000100010001000 H
b11110 .
b11110 B
b11110 4
b11110 %
b1000100010001001000100010001011110100 &
b11110 8
b11110 )
b100001 ?
b100000 @
1!
1#
#330
0!
0#
#335
b0 '
b0 /
b0 D
b0 E
b10010001000100010000000000000000 F
b10001000100100010001000100000000 G
b10001000100010010001000100010000 H
1h
b100010001000100100010001000100 I
b11111 .
b11111 B
b11111 4
b11111 %
b1000100010001001000100010001011111100 &
b11111 8
b11111 )
b100010 ?
b100001 @
1!
1#
#340
0!
0#
