fsl/mult32/mult32.v
/*
 * This code is produced by: 
 *   FSL Compiler version 0.1 alpha (2020-05-19) build 20E314
 *   Designed by Nobuya WATANABE, Okayama University, 2015-2020.
 * 
 *   Mon Jun 08 23:18:45 JST 2020
 * 
 * The source file of this code: 'mult32.fsl'.
 * 
 * INFO: 
 * 
 */
/* ModuleDef: mult32 */

module mult32(p_reset, m_clock, a, b, out, en, mult);
  input         p_reset;
  wire          p_reset;
  input         m_clock;
  wire          m_clock;
  input  [31:0] a;
  wire   [31:0] a;
  input  [31:0] b;
  wire   [31:0] b;
  output [63:0] out;
  wire   [63:0] out;
  output        en;
  wire          en;
  input         mult;
  wire          mult;
  /* for bundle-type input/output */
  /* local decls */
  wire          __net0;
  wire          __net1;
  wire          __net10;
  wire          __net11;
  wire          __net12;
  wire          __net13;
  wire          __net14;
  wire          __net15;
  wire          __net16;
  wire          __net17;
  wire          __net18;
  wire          __net19;
  wire          __net2;
  wire          __net20;
  wire          __net21;
  wire          __net22;
  wire          __net23;
  wire          __net24;
  wire          __net25;
  wire          __net26;
  wire          __net27;
  wire          __net28;
  wire          __net29;
  wire          __net3;
  wire          __net30;
  wire          __net31;
  wire   [63:0] __net32;
  wire          __net4;
  wire          __net5;
  wire          __net6;
  wire          __net7;
  wire          __net8;
  wire          __net9;
  /* assigns */
  assign __net0 = mult ? b[0:0] == 1'B1 ? 1'b1 : 1'b0 : 1'bx;
  assign __net1 = mult ? b[1:1] == 1'B1 ? 1'b1 : 1'b0 : 1'bx;
  assign __net10 = mult ? b[10:10] == 1'B1 ? 1'b1 : 1'b0 : 1'bx;
  assign __net11 = mult ? b[11:11] == 1'B1 ? 1'b1 : 1'b0 : 1'bx;
  assign __net12 = mult ? b[12:12] == 1'B1 ? 1'b1 : 1'b0 : 1'bx;
  assign __net13 = mult ? b[13:13] == 1'B1 ? 1'b1 : 1'b0 : 1'bx;
  assign __net14 = mult ? b[14:14] == 1'B1 ? 1'b1 : 1'b0 : 1'bx;
  assign __net15 = mult ? b[15:15] == 1'B1 ? 1'b1 : 1'b0 : 1'bx;
  assign __net16 = mult ? b[16:16] == 1'B1 ? 1'b1 : 1'b0 : 1'bx;
  assign __net17 = mult ? b[17:17] == 1'B1 ? 1'b1 : 1'b0 : 1'bx;
  assign __net18 = mult ? b[18:18] == 1'B1 ? 1'b1 : 1'b0 : 1'bx;
  assign __net19 = mult ? b[19:19] == 1'B1 ? 1'b1 : 1'b0 : 1'bx;
  assign __net2 = mult ? b[2:2] == 1'B1 ? 1'b1 : 1'b0 : 1'bx;
  assign __net20 = mult ? b[20:20] == 1'B1 ? 1'b1 : 1'b0 : 1'bx;
  assign __net21 = mult ? b[21:21] == 1'B1 ? 1'b1 : 1'b0 : 1'bx;
  assign __net22 = mult ? b[22:22] == 1'B1 ? 1'b1 : 1'b0 : 1'bx;
  assign __net23 = mult ? b[23:23] == 1'B1 ? 1'b1 : 1'b0 : 1'bx;
  assign __net24 = mult ? b[24:24] == 1'B1 ? 1'b1 : 1'b0 : 1'bx;
  assign __net25 = mult ? b[25:25] == 1'B1 ? 1'b1 : 1'b0 : 1'bx;
  assign __net26 = mult ? b[26:26] == 1'B1 ? 1'b1 : 1'b0 : 1'bx;
  assign __net27 = mult ? b[27:27] == 1'B1 ? 1'b1 : 1'b0 : 1'bx;
  assign __net28 = mult ? b[28:28] == 1'B1 ? 1'b1 : 1'b0 : 1'bx;
  assign __net29 = mult ? b[29:29] == 1'B1 ? 1'b1 : 1'b0 : 1'bx;
  assign __net3 = mult ? b[3:3] == 1'B1 ? 1'b1 : 1'b0 : 1'bx;
  assign __net30 = mult ? b[30:30] == 1'B1 ? 1'b1 : 1'b0 : 1'bx;
  assign __net31 = mult ? b[31:31] == 1'B1 ? 1'b1 : 1'b0 : 1'bx;
  assign __net32 = mult ? 
                     ((b[0:0] == 1'B1 ? 
                       {a, 32'B00000000000000000000000000000000} : 
                       64'B0000000000000000000000000000000000000000000000000000000000000000) >> 32) + ((b[1:1] == 1'B1 ? 
                       {a, 32'B00000000000000000000000000000000} : 
                       64'B0000000000000000000000000000000000000000000000000000000000000000) >> 31) + ((b[2:2] == 1'B1 ? 
                       {a, 32'B00000000000000000000000000000000} : 
                       64'B0000000000000000000000000000000000000000000000000000000000000000) >> 30) + ((b[3:3] == 1'B1 ? 
                       {a, 32'B00000000000000000000000000000000} : 
                       64'B0000000000000000000000000000000000000000000000000000000000000000) >> 29) + ((b[4:4] == 1'B1 ? 
                       {a, 32'B00000000000000000000000000000000} : 
                       64'B0000000000000000000000000000000000000000000000000000000000000000) >> 28) + ((b[5:5] == 1'B1 ? 
                       {a, 32'B00000000000000000000000000000000} : 
                       64'B0000000000000000000000000000000000000000000000000000000000000000) >> 27) + ((b[6:6] == 1'B1 ? 
                       {a, 32'B00000000000000000000000000000000} : 
                       64'B0000000000000000000000000000000000000000000000000000000000000000) >> 26) + ((b[7:7] == 1'B1 ? 
                       {a, 32'B00000000000000000000000000000000} : 
                       64'B0000000000000000000000000000000000000000000000000000000000000000) >> 25) + ((b[8:8] == 1'B1 ? 
                       {a, 32'B00000000000000000000000000000000} : 
                       64'B0000000000000000000000000000000000000000000000000000000000000000) >> 24) + ((b[9:9] == 1'B1 ? 
                       {a, 32'B00000000000000000000000000000000} : 
                       64'B0000000000000000000000000000000000000000000000000000000000000000) >> 23) + ((b[10:10] == 1'B1 ? 
                       {a, 32'B00000000000000000000000000000000} : 
                       64'B0000000000000000000000000000000000000000000000000000000000000000) >> 22) + ((b[11:11] == 1'B1 ? 
                       {a, 32'B00000000000000000000000000000000} : 
                       64'B0000000000000000000000000000000000000000000000000000000000000000) >> 21) + ((b[12:12] == 1'B1 ? 
                       {a, 32'B00000000000000000000000000000000} : 
                       64'B0000000000000000000000000000000000000000000000000000000000000000) >> 20) + ((b[13:13] == 1'B1 ? 
                       {a, 32'B00000000000000000000000000000000} : 
                       64'B0000000000000000000000000000000000000000000000000000000000000000) >> 19) + ((b[14:14] == 1'B1 ? 
                       {a, 32'B00000000000000000000000000000000} : 
                       64'B0000000000000000000000000000000000000000000000000000000000000000) >> 18) + ((b[15:15] == 1'B1 ? 
                       {a, 32'B00000000000000000000000000000000} : 
                       64'B0000000000000000000000000000000000000000000000000000000000000000) >> 17) + ((b[16:16] == 1'B1 ? 
                       {a, 32'B00000000000000000000000000000000} : 
                       64'B0000000000000000000000000000000000000000000000000000000000000000) >> 16) + ((b[17:17] == 1'B1 ? 
                       {a, 32'B00000000000000000000000000000000} : 
                       64'B0000000000000000000000000000000000000000000000000000000000000000) >> 15) + ((b[18:18] == 1'B1 ? 
                       {a, 32'B00000000000000000000000000000000} : 
                       64'B0000000000000000000000000000000000000000000000000000000000000000) >> 14) + ((b[19:19] == 1'B1 ? 
                       {a, 32'B00000000000000000000000000000000} : 
                       64'B0000000000000000000000000000000000000000000000000000000000000000) >> 13) + ((b[20:20] == 1'B1 ? 
                       {a, 32'B00000000000000000000000000000000} : 
                       64'B0000000000000000000000000000000000000000000000000000000000000000) >> 12) + ((b[21:21] == 1'B1 ? 
                       {a, 32'B00000000000000000000000000000000} : 
                       64'B0000000000000000000000000000000000000000000000000000000000000000) >> 11) + ((b[22:22] == 1'B1 ? 
                       {a, 32'B00000000000000000000000000000000} : 
                       64'B0000000000000000000000000000000000000000000000000000000000000000) >> 10) + ((b[23:23] == 1'B1 ? 
                       {a, 32'B00000000000000000000000000000000} : 
                       64'B0000000000000000000000000000000000000000000000000000000000000000) >> 9) + ((b[24:24] == 1'B1 ? 
                       {a, 32'B00000000000000000000000000000000} : 
                       64'B0000000000000000000000000000000000000000000000000000000000000000) >> 8) + ((b[25:25] == 1'B1 ? 
                       {a, 32'B00000000000000000000000000000000} : 
                       64'B0000000000000000000000000000000000000000000000000000000000000000) >> 7) + ((b[26:26] == 1'B1 ? 
                       {a, 32'B00000000000000000000000000000000} : 
                       64'B0000000000000000000000000000000000000000000000000000000000000000) >> 6) + ((b[27:27] == 1'B1 ? 
                       {a, 32'B00000000000000000000000000000000} : 
                       64'B0000000000000000000000000000000000000000000000000000000000000000) >> 5) + ((b[28:28] == 1'B1 ? 
                       {a, 32'B00000000000000000000000000000000} : 
                       64'B0000000000000000000000000000000000000000000000000000000000000000) >> 4) + ((b[29:29] == 1'B1 ? 
                       {a, 32'B00000000000000000000000000000000} : 
                       64'B0000000000000000000000000000000000000000000000000000000000000000) >> 3) + ((b[30:30] == 1'B1 ? 
                       {a, 32'B00000000000000000000000000000000} : 
                       64'B0000000000000000000000000000000000000000000000000000000000000000) >> 2) + ((b[31:31] == 1'B1 ? 
                       {a, 32'B00000000000000000000000000000000} : 
                       64'B0000000000000000000000000000000000000000000000000000000000000000) >> 1) : 
                     64'bx;
  assign __net4 = mult ? b[4:4] == 1'B1 ? 1'b1 : 1'b0 : 1'bx;
  assign __net5 = mult ? b[5:5] == 1'B1 ? 1'b1 : 1'b0 : 1'bx;
  assign __net6 = mult ? b[6:6] == 1'B1 ? 1'b1 : 1'b0 : 1'bx;
  assign __net7 = mult ? b[7:7] == 1'B1 ? 1'b1 : 1'b0 : 1'bx;
  assign __net8 = mult ? b[8:8] == 1'B1 ? 1'b1 : 1'b0 : 1'bx;
  assign __net9 = mult ? b[9:9] == 1'B1 ? 1'b1 : 1'b0 : 1'bx;
  assign out = mult ? __net32 : 64'bx;
  /* invokes */
  /* private function */
  assign en = mult;
  /* defs */
  /* FunDef mult */
  /*   parameter: a: Bit(32) */
  /*   parameter: b: Bit(32) */
endmodule
/* End of file (mult32.v) */

fsl/mult32/test_mult32.v
/*
 * This code is produced by: 
 *   FSL Compiler version 0.1 alpha (2020-05-19) build 20E314
 *   Designed by Nobuya WATANABE, Okayama University, 2015-2020.
 * 
 *   Mon Jun 08 23:18:45 JST 2020
 * 
 * The source file of this code: 'test_mult32.fsl'.
 * 
 * INFO: 
 * 
 */
/* ModuleDef: test_mult32 */

module test_mult32(p_reset, m_clock);
  input         p_reset;
  wire          p_reset;
  input         m_clock;
  wire          m_clock;
  /* for bundle-type input/output */
  /* param decls */
  parameter _stage_test_state_st3 = 0;
  parameter _stage_test_state_st2 = 1;
  parameter _stage_test_state_st1 = 2;
  parameter _stage_test_state_st0 = 3;
  /* decls */
  /* ModuleInstance: m0: ___no_package___.mult32 */
  wire          _m0_p_reset;
  wire          _m0_m_clock;
  wire   [31:0] _m0_b;
  wire          _m0_en;
  wire   [31:0] _m0_a;
  wire          _m0_mult;
  wire   [63:0] _m0_out;
  mult32 m0(.p_reset(_m0_p_reset),
            .m_clock(_m0_m_clock),
            .b(_m0_b),
            .en(_m0_en),
            .a(_m0_a),
            .mult(_m0_mult),
            .out(_m0_out));
  /* reg decl */
  reg    [15:0] count;
  /* reg decl */
  reg    [11:0] n_ok;
  /* reg decl */
  reg    [11:0] n_fail;
  /* MemDecl pat (BitType 128) size: IConst(2000,2000) */
  reg   [127:0] pat[0:1999];
  /* local decls */
  wire          __net0;
  wire          __net1;
  wire          __net10;
  wire          __net11;
  wire   [11:0] __net12;
  wire   [31:0] __net13;
  wire   [31:0] __net14;
  wire   [63:0] __net15;
  wire   [63:0] __net16;
  wire          __net17;
  wire          __net18;
  wire          __net19;
  wire          __net2;
  wire   [11:0] __net20;
  wire   [31:0] __net21;
  wire   [31:0] __net22;
  wire   [63:0] __net23;
  wire   [63:0] __net24;
  wire          __net25;
  wire          __net3;
  wire          __net4;
  wire          __net5;
  wire          __net6;
  wire   [11:0] __net7;
  wire   [31:0] __net8;
  wire   [31:0] __net9;
  wire          __stage_test_reset;
  wire          __stage_test_set;
  wire   [31:0] _check_a;
  wire   [31:0] _check_b;
  wire   [11:0] _check_i;
  wire   [63:0] _check_o;
  wire   [63:0] _check_out;
  wire   [31:0] _test_st2_4_a;
  wire   [31:0] _test_st2_4_b;
  wire   [63:0] _test_st2_4_o;
  wire  [127:0] _test_st2_4_p;
  wire          check;
  wire          stop;
  /* reg decls */
  reg           _stage_test_reg;
  reg     [1:0] _stage_test_state_reg;
  /* reg decls (system) */
  reg    [63:0] _time;
  /* assigns */
  assign __net0 = _time == 64'b10 ? 1'b1 : 1'b0;
  assign __net1 = count == 1 ? 1'b1 : 1'b0;
  assign __net10 = _stage_test_reg & __net6 ? _m0_en : 1'bx;
  assign __net11 = _stage_test_reg & __net6 ? _m0_en ? 1'b1 : 1'b0 : 1'bx;
  assign __net12 = _stage_test_reg & __net6 & __net11 ? 
                     _stage_test_reg_ii : 
                     12'bx;
  assign __net13 = _stage_test_reg & __net6 & __net11 ? 
                     _test_st2_4_a : 
                     32'bx;
  assign __net14 = _stage_test_reg & __net6 & __net11 ? 
                     _test_st2_4_b : 
                     32'bx;
  assign __net15 = _stage_test_reg & __net6 & __net11 ? _m0_out : 64'bx;
  assign __net16 = _stage_test_reg & __net6 & __net11 ? 
                     _test_st2_4_o : 
                     64'bx;
  assign __net18 = _stage_test_reg & __net17 ? _m0_en : 1'bx;
  assign __net19 = _stage_test_reg & __net17 ? _m0_en ? 1'b1 : 1'b0 : 1'bx;
  assign __net2 = count == 10000 ? 1'b1 : 1'b0;
  assign __net20 = _stage_test_reg & __net17 & __net19 ? 
                     _stage_test_reg_ii : 
                     12'bx;
  assign __net21 = _stage_test_reg & __net17 & __net19 ? 
                     _stage_test_reg_aa : 
                     32'bx;
  assign __net22 = _stage_test_reg & __net17 & __net19 ? 
                     _stage_test_reg_bb : 
                     32'bx;
  assign __net23 = _stage_test_reg & __net17 & __net19 ? _m0_out : 64'bx;
  assign __net24 = _stage_test_reg & __net17 & __net19 ? 
                     _stage_test_reg_oo : 
                     64'bx;
  assign __net25 = check ? _check_out == _check_o ? 1'b1 : 1'b0 : 1'bx;
  assign __net5 = _stage_test_reg & __net4 ? 
                    _stage_test_reg_ii < 2000 ? 
                      1'b1 : 
                      1'b0 : 
                    1'bx;
  assign __net7 = _stage_test_reg & __net6 ? _stage_test_reg_ii : 12'bx;
  assign __net8 = _stage_test_reg & __net6 ? _test_st2_4_a : 32'bx;
  assign __net9 = _stage_test_reg & __net6 ? _test_st2_4_b : 32'bx;
  assign __stage_test_reset = _stage_test_reg & __net4 & ~__net5 ? 
                                1'b1 : 
                                1'b0;
  assign __stage_test_set = __net1 ? 1'b1 : 1'b0;
  assign _check_a = _stage_test_reg & __net6 & __net11 ? 
                      __net13 : 
                      _stage_test_reg & __net17 & __net19 ? 
                        __net21 : 
                        32'bx;
  assign _check_b = _stage_test_reg & __net6 & __net11 ? 
                      __net14 : 
                      _stage_test_reg & __net17 & __net19 ? 
                        __net22 : 
                        32'bx;
  assign _check_i = _stage_test_reg & __net6 & __net11 ? 
                      __net12 : 
                      _stage_test_reg & __net17 & __net19 ? 
                        __net20 : 
                        12'bx;
  assign _check_o = _stage_test_reg & __net6 & __net11 ? 
                      __net16 : 
                      _stage_test_reg & __net17 & __net19 ? 
                        __net24 : 
                        64'bx;
  assign _check_out = _stage_test_reg & __net6 & __net11 ? 
                        __net15 : 
                        _stage_test_reg & __net17 & __net19 ? 
                          __net23 : 
                          64'bx;
  assign _m0_a = _stage_test_reg & __net6 ? __net8 : 32'bx;
  assign _m0_b = _stage_test_reg & __net6 ? __net9 : 32'bx;
  assign _m0_m_clock = m_clock;
  assign _m0_mult = _stage_test_reg & __net6 ? 1'b1 : 1'b0;
  assign _m0_p_reset = p_reset;
  assign _test_st2_4_a = _stage_test_reg & __net6 ? 
                           _test_st2_4_p[127:96] : 
                           32'bx;
  assign _test_st2_4_b = _stage_test_reg & __net6 ? 
                           _test_st2_4_p[95:64] : 
                           32'bx;
  assign _test_st2_4_o = _stage_test_reg & __net6 ? 
                           _test_st2_4_p[63:0] : 
                           64'bx;
  assign _test_st2_4_p = _stage_test_reg & __net6 ? pat[__net7] : 128'bx;
  /* invokes */
  /* private function */
  assign stop = __net2 | _stage_test_reg & __net4 & ~__net5;
  assign check = _stage_test_reg & __net6 & __net11 | _stage_test_reg & __net17 & __net19;
  /* defs */
  /* initial */
  /* always */
  /* FunDef (private): stop */
  /* BlockExpr */
  /* SystemTaskFun: '$display' */
  /* SystemTaskFun: '$finish' */
  /* StageDef: test */
  /* StageBody */
  /* reg decl */
  reg    [11:0] _stage_test_reg_ii;
  /* reg decl */
  reg    [31:0] _stage_test_reg_aa;
  /* reg decl */
  reg    [31:0] _stage_test_reg_bb;
  /* reg decl */
  reg    [63:0] _stage_test_reg_oo;
  /* StateDef: st0:  */
  assign __net3 = _stage_test_state_reg == _stage_test_state_st0;
  /* par */
  /* goto: st2 */
  /* StateDef: st1:  */
  assign __net4 = _stage_test_state_reg == _stage_test_state_st1;
  /* StateDef: st2:  */
  assign __net6 = _stage_test_state_reg == _stage_test_state_st2;
  /* par */
  /* invoke: m0.mult */
  /* invoke */
  /* StateDef: st3:  */
  assign __net17 = _stage_test_state_reg == _stage_test_state_st3;
  /* stage reg updates */
  always @(posedge m_clock or posedge p_reset)
    begin
      if (p_reset)
        _stage_test_reg <= 1'b0;
      else if (__stage_test_set | __stage_test_reset)
        _stage_test_reg <= __stage_test_set;
    end
  /* stage params updates */
  /* stage: test: params:  */
  /* reg updates */
  always @(posedge m_clock or posedge p_reset)
    begin
      if (p_reset)
        _stage_test_reg_oo <= 1'b0;
      else if (_stage_test_reg & __net6 & ~__net11)
        _stage_test_reg_oo <= _test_st2_4_o;
    end
  always @(posedge m_clock or posedge p_reset)
    begin
      if (p_reset)
        count <= 16'b0;
      else
        count <= count + 16'B0000000000000001;
    end
  always @(posedge m_clock or posedge p_reset)
    begin
      if (p_reset)
        n_fail <= 12'b0;
      else if (__net0)
        n_fail <= 0;
      else if (check & ~__net25)
        n_fail <= n_fail + 12'B000000000001;
    end
  always @(posedge m_clock or posedge p_reset)
    begin
      if (p_reset)
        _stage_test_reg_bb <= 1'b0;
      else if (_stage_test_reg & __net6 & ~__net11)
        _stage_test_reg_bb <= _test_st2_4_b;
    end
  always @(posedge m_clock or posedge p_reset)
    begin
      if (p_reset)
        _stage_test_reg_ii <= 1'b0;
      else if (_stage_test_reg & __net3)
        _stage_test_reg_ii <= 0;
      else if (_stage_test_reg & __net6 & __net11)
        _stage_test_reg_ii <= _stage_test_reg_ii + 12'B000000000001;
      else if (_stage_test_reg & __net17 & __net19)
        _stage_test_reg_ii <= _stage_test_reg_ii + 12'B000000000001;
    end
  always @(posedge m_clock or posedge p_reset)
    begin
      if (p_reset)
        n_ok <= 12'b0;
      else if (__net0)
        n_ok <= 0;
      else if (check & __net25)
        n_ok <= n_ok + 12'B000000000001;
    end
  always @(posedge m_clock or posedge p_reset)
    begin
      if (p_reset)
        _stage_test_reg_aa <= 1'b0;
      else if (_stage_test_reg & __net6 & ~__net11)
        _stage_test_reg_aa <= _test_st2_4_a;
    end
  /* reg updates (system) */
  always @(posedge m_clock)
    begin
      _time <= _time + 64'b1;
    end
  /* state reg updates */
  always @(posedge m_clock or posedge p_reset)
    begin
      if (p_reset)
        _stage_test_state_reg <= _stage_test_state_st0;
      else if (_stage_test_reg & __net3)
        _stage_test_state_reg <= _stage_test_state_st2;
      else if (_stage_test_reg & __net4 & __net5)
        _stage_test_state_reg <= _stage_test_state_st2;
      else if (_stage_test_reg & __net4 & ~__net5)
        _stage_test_state_reg <= _stage_test_state_st0;
      else if (_stage_test_reg & __net6 & __net11)
        _stage_test_state_reg <= _stage_test_state_st1;
      else if (_stage_test_reg & __net6 & ~__net11)
        _stage_test_state_reg <= _stage_test_state_st3;
      else if (_stage_test_reg & __net17 & __net19)
        _stage_test_state_reg <= _stage_test_state_st1;
    end
  /* always */
  always @(posedge m_clock)
    if (check & ~__net25)
      $display("%d %x %x - %x %x... fail", _check_i, _check_a, _check_b, _check_out, _check_o);
  always @(posedge m_clock)
    if (check & __net25)
      $display("%d %x %x - %x ... ok", _check_i, _check_a, _check_b, _check_out);
  always @(posedge m_clock)
    if (stop)
      $display("%d: bye.", count);
  always @(posedge m_clock)
    if (stop)
      $finish();
  always @(posedge m_clock)
    if (stop)
      $display("ok: %d, fail: %d", n_ok, n_fail);
  always @(posedge m_clock)
    if (__net0)
      $readmemb("test_mult32.pat", pat);
  /* initial (system) */
  initial begin
    _time <= 64'b0;
  end
endmodule
/* test bench: 'tb' */

module tb;
  parameter CYCLE_TIME = 10;
  reg p_reset;
  reg m_clock;
  test_mult32 test_mult32_instance(.p_reset(p_reset),
                                   .m_clock(m_clock));
  initial begin
    forever #(CYCLE_TIME / 2) m_clock = ~m_clock;
  end
  initial begin
    $dumpfile("test_mult32.vcd");
    $dumpvars(0, test_mult32_instance);
  end
  initial begin
    #(CYCLE_TIME / 10) begin
      p_reset = 1;
      m_clock = 0;
    end
    #CYCLE_TIME p_reset = 0;
  end
endmodule
/* End of file (test_mult32.v) */

fsl/mult32/test_mult32.vcd
$date
	Mon Jun  8 23:18:52 2020
$end
$version
	Icarus Verilog
$end
$timescale
	1s
$end
$scope module tb $end
$scope module test_mult32_instance $end
$var wire 1 ! _m0_m_clock $end
$var wire 1 " _m0_p_reset $end
$var wire 1 # check $end
$var wire 1 $ m_clock $end
$var wire 1 % p_reset $end
$var wire 1 & stop $end
$var wire 128 ' _test_st2_4_p [127:0] $end
$var wire 64 ( _test_st2_4_o [63:0] $end
$var wire 32 ) _test_st2_4_b [31:0] $end
$var wire 32 * _test_st2_4_a [31:0] $end
$var wire 64 + _m0_out [63:0] $end
$var wire 1 , _m0_mult $end
$var wire 1 - _m0_en $end
$var wire 32 . _m0_b [31:0] $end
$var wire 32 / _m0_a [31:0] $end
$var wire 64 0 _check_out [63:0] $end
$var wire 64 1 _check_o [63:0] $end
$var wire 12 2 _check_i [11:0] $end
$var wire 32 3 _check_b [31:0] $end
$var wire 32 4 _check_a [31:0] $end
$var wire 1 5 __stage_test_set $end
$var wire 1 6 __stage_test_reset $end
$var wire 32 7 __net9 [31:0] $end
$var wire 32 8 __net8 [31:0] $end
$var wire 12 9 __net7 [11:0] $end
$var wire 1 : __net6 $end
$var wire 1 ; __net5 $end
$var wire 1 < __net4 $end
$var wire 1 = __net3 $end
$var wire 1 > __net25 $end
$var wire 64 ? __net24 [63:0] $end
$var wire 64 @ __net23 [63:0] $end
$var wire 32 A __net22 [31:0] $end
$var wire 32 B __net21 [31:0] $end
$var wire 12 C __net20 [11:0] $end
$var wire 1 D __net2 $end
$var wire 1 E __net19 $end
$var wire 1 F __net18 $end
$var wire 1 G __net17 $end
$var wire 64 H __net16 [63:0] $end
$var wire 64 I __net15 [63:0] $end
$var wire 32 J __net14 [31:0] $end
$var wire 32 K __net13 [31:0] $end
$var wire 12 L __net12 [11:0] $end
$var wire 1 M __net11 $end
$var wire 1 N __net10 $end
$var wire 1 O __net1 $end
$var wire 1 P __net0 $end
$var reg 1 Q _stage_test_reg $end
$var reg 32 R _stage_test_reg_aa [31:0] $end
$var reg 32 S _stage_test_reg_bb [31:0] $end
$var reg 12 T _stage_test_reg_ii [11:0] $end
$var reg 64 U _stage_test_reg_oo [63:0] $end
$var reg 2 V _stage_test_state_reg [1:0] $end
$var reg 64 W _time [63:0] $end
$var reg 16 X count [15:0] $end
$var reg 12 Y n_fail [11:0] $end
$var reg 12 Z n_ok [11:0] $end
$scope module m0 $end
$var wire 32 [ a [31:0] $end
$var wire 32 \ b [31:0] $end
$var wire 1 - en $end
$var wire 1 ! m_clock $end
$var wire 1 , mult $end
$var wire 1 " p_reset $end
$var wire 64 ] out [63:0] $end
$var wire 1 ^ __net9 $end
$var wire 1 _ __net8 $end
$var wire 1 ` __net7 $end
$var wire 1 a __net6 $end
$var wire 1 b __net5 $end
$var wire 1 c __net4 $end
$var wire 64 d __net32 [63:0] $end
$var wire 1 e __net31 $end
$var wire 1 f __net30 $end
$var wire 1 g __net3 $end
$var wire 1 h __net29 $end
$var wire 1 i __net28 $end
$var wire 1 j __net27 $end
$var wire 1 k __net26 $end
$var wire 1 l __net25 $end
$var wire 1 m __net24 $end
$var wire 1 n __net23 $end
$var wire 1 o __net22 $end
$var wire 1 p __net21 $end
$var wire 1 q __net20 $end
$var wire 1 r __net2 $end
$var wire 1 s __net19 $end
$var wire 1 t __net18 $end
$var wire 1 u __net17 $end
$var wire 1 v __net16 $end
$var wire 1 w __net15 $end
$var wire 1 x __net14 $end
$var wire 1 y __net13 $end
$var wire 1 z __net12 $end
$var wire 1 { __net11 $end
$var wire 1 | __net10 $end
$var wire 1 } __net1 $end
$var wire 1 ~ __net0 $end
$upscope $end
$upscope $end
$upscope $end
$enddefinitions $end
#0
$dumpvars
x~
x}
x|
x{
xz
xy
xx
xw
xv
xu
xt
xs
xr
xq
xp
xo
xn
xm
xl
xk
xj
xi
xh
xg
xf
xe
bx d
xc
xb
xa
x`
x_
x^
bx ]
bx \
bx [
bx Z
bx Y
bx X
b0 W
bx V
bx U
bx T
bx S
bx R
xQ
0P
xO
xN
xM
bx L
bx K
bx J
bx I
bx H
xG
xF
xE
xD
bx C
bx B
bx A
bx @
bx ?
x>
x=
x<
x;
x:
bx 9
bx 8
bx 7
x6
x5
bx 4
bx 3
bx 2
bx 1
bx 0
bx /
bx .
x-
x,
bx +
bx *
bx )
bx (
bx '
x&
x%
x$
x#
x"
x!
$end
#1
06
0#
05
0&
0-
0,
0O
0D
0Q
b0 U
b0 X
b0 Y
b0 S
b0 T
b0 Z
b0 R
1=
0<
0:
0G
b11 V
0!
0$
1"
1%
#5
b1 W
1!
1$
#10
0!
0$
#11
0"
0%
#15
15
1P
1O
b10 W
b1 X
1!
1$
#20
0!
0$
#25
05
0P
0O
b11 W
b10 X
1Q
1!
1$
#30
0!
0$
#35
1>
b1001110100111100100101100100011001000011101010100000101110010101 0
b1001110100111100100101100100011001000011101010100000101110010101 I
b1001110100111100100101100100011001000011101010100000101110010101 +
b1001110100111100100101100100011001000011101010100000101110010101 ]
b1001110100111100100101100100011001000011101010100000101110010101 d
1~
0}
0|
0{
1z
0y
1x
0w
0v
1u
0t
1s
1r
1q
0p
0o
1n
1m
1l
0k
0j
1i
1h
0g
1f
1e
0c
0b
0a
0`
1_
0^
b11110011100110100101000100000101 .
b11110011100110100101000100000101 \
b10100101001111010001010101010001 /
b10100101001111010001010101010001 [
1#
b1001110100111100100101100100011001000011101010100000101110010101 1
b0 2
b11110011100110100101000100000101 3
b10100101001111010001010101010001 4
b1001110100111100100101100100011001000011101010100000101110010101 H
b11110011100110100101000100000101 J
b10100101001111010001010101010001 K
b0 L
b11110011100110100101000100000101 7
b10100101001111010001010101010001 8
b1001110100111100100101100100011001000011101010100000101110010101 (
b11110011100110100101000100000101 )
b10100101001111010001010101010001 *
b10100101001111010001010101010001111100111001101001010001000001011001110100111100100101100100011001000011101010100000101110010101 '
1-
1,
b0 9
1M
1N
b100 W
b11 X
0=
1:
b1 V
1!
1$
#40
0!
0$
#45
x>
0&
06
0#
x~
x}
x|
x{
xz
xy
xx
xw
xv
xu
xt
xs
xr
xq
xp
xo
xn
xm
xl
xk
xj
xi
xh
xg
xf
xe
bx d
xc
xb
xa
x`
x_
x^
bx +
bx ]
bx 0
bx 1
bx 3
bx 4
bx H
bx I
bx J
bx K
1;
bx (
bx )
bx *
0-
0,
bx .
bx \
bx /
bx [
bx 7
bx 8
xM
xN
bx 2
bx '
bx L
bx 9
b101 W
1<
0:
b10 V
b1 Z
b1 T
b100 X
1!
1$
#50
0!
0$
#55
1>
b100100110101000000101110001100111001000110111010101111100001010 0
b100100110101000000101110001100111001000110111010101111100001010 I
b100100110101000000101110001100111001000110111010101111100001010 +
b100100110101000000101110001100111001000110111010101111100001010 ]
b100100110101000000101110001100111001000110111010101111100001010 d
1~
1}
0|
1{
1z
0y
1x
0w
0v
1u
0t
0s
0r
0q
1p
1o
0n
0m
0l
1k
0j
1i
0h
1g
1f
0e
0c
0b
1a
1`
0_
1^
b1010100011000100101101011001011 .
b1010100011000100101101011001011 \
b11011111011101001000100111011110 /
b11011111011101001000100111011110 [
1#
b100100110101000000101110001100111001000110111010101111100001010 1
b1 2
b1010100011000100101101011001011 3
b11011111011101001000100111011110 4
b100100110101000000101110001100111001000110111010101111100001010 H
b1010100011000100101101011001011 J
b11011111011101001000100111011110 K
b1 L
b1010100011000100101101011001011 7
b11011111011101001000100111011110 8
b100100110101000000101110001100111001000110111010101111100001010 (
b1010100011000100101101011001011 )
b11011111011101001000100111011110 *
x;
b11011111011101001000100111011110010101000110001001011010110010110100100110101000000101110001100111001000110111010101111100001010 '
1-
1,
b1 9
1M
1N
b110 W
b101 X
0<
1:
b1 V
1!
1$
#60
0!
0$
#65
x>
0&
06
0#
x~
x}
x|
x{
xz
xy
xx
xw
xv
xu
xt
xs
xr
xq
xp
xo
xn
xm
xl
xk
xj
xi
xh
xg
xf
xe
bx d
xc
xb
xa
x`
x_
x^
bx +
bx ]
bx 0
bx 1
bx 3
bx 4
bx H
bx I
bx J
bx K
1;
bx (
bx )
bx *
0-
0,
bx .
bx \
bx /
bx [
bx 7
bx 8
xM
xN
bx 2
bx '
bx L
bx 9
b111 W
1<
0:
b10 V
b10 Z
b10 T
b110 X
1!
1$
#70
0!
0$
